{
  "14cbf8b021d556bbf6d5e0f44d716c98580fc9e1": {
    "resultcheckpatch-parallel": "0",
    "enforcedcheckpatch-parallel": "False",
    "runtimecheckpatch-parallel": "530",
    "descriptioncheckpatch-parallel": "Run checkpatch.pl on the entire Lustre tree",
    "resultcontribution-report": "0",
    "enforcedcontribution-report": "False",
    "runtimecontribution-report": "449",
    "descriptioncontribution-report": "Fetch contribution statistics for Lustre tree",
    "resultlicense-status": "0",
    "enforcedlicense-status": "False",
    "runtimelicense-status": "459",
    "descriptionlicense-status": "Fetch license info for Lustre tree",
    "resultkernel-doc": "0",
    "enforcedkernel-doc": "False",
    "runtimekernel-doc": "452",
    "descriptionkernel-doc": "Check the number of kernel doc errors",
    "resultu24": "0",
    "enforcedu24": "True",
    "runtimeu24": "574",
    "descriptionu24": "Build Lustre (U24/OutOfTree)",
    "resultal2023": "0",
    "enforcedal2023": "True",
    "runtimeal2023": "541",
    "descriptional2023": "Build Lustre (AL2023/OutOfTree)",
    "resultlustre_mainline_strict": "1",
    "enforcedlustre_mainline_strict": "False",
    "runtimelustre_mainline_strict": "790",
    "descriptionlustre_mainline_strict": "Build Lustre (LLVM/OutOfTree/NoWarnings)",
    "resultlustre_mainline": "0",
    "enforcedlustre_mainline": "True",
    "runtimelustre_mainline": "794",
    "descriptionlustre_mainline": "Build Lustre (LLVM/OutOfTree)",
    "resultlustre_mainline_native": "0",
    "enforcedlustre_mainline_native": "True",
    "runtimelustre_mainline_native": "795",
    "descriptionlustre_mainline_native": "Build Lustre (InTree)",
    "resultclang-tidy": "0",
    "enforcedclang-tidy": "False",
    "runtimeclang-tidy": "86",
    "descriptionclang-tidy": "Run Clang Tidy",
    "resultcc-plugin": "127",
    "enforcedcc-plugin": "False",
    "runtimecc-plugin": "57",
    "descriptioncc-plugin": "Run Lustre LLVM Compiler Plugin",
    "resultboot": "0",
    "enforcedboot": "True",
    "runtimeboot": "65",
    "descriptionboot": "Job: boot",
    "resultllmount": "0",
    "enforcedllmount": "True",
    "runtimellmount": "152",
    "descriptionllmount": "Job: llmount",
    "resultmgs-setup": "0",
    "enforcedmgs-setup": "True",
    "runtimemgs-setup": "77",
    "descriptionmgs-setup": "Job: mgs-setup",
    "resultsanity-1": "0",
    "enforcedsanity-1": "True",
    "runtimesanity-1": "107",
    "descriptionsanity-1": "Job: sanity-1",
    "resultsanity-2": "0",
    "enforcedsanity-2": "True",
    "runtimesanity-2": "91",
    "descriptionsanity-2": "Job: sanity-2",
    "resultsanity-3": "0",
    "enforcedsanity-3": "True",
    "runtimesanity-3": "92",
    "descriptionsanity-3": "Job: sanity-3",
    "resultsanity-4": "0",
    "enforcedsanity-4": "True",
    "runtimesanity-4": "92",
    "descriptionsanity-4": "Job: sanity-4",
    "patch_revision": "14cbf8b021d556bbf6d5e0f44d716c98580fc9e1",
    "time_stamp": "1778533209",
    "total_runtime": "978",
    "change_id": "master",
    "subject": "Main development branch",
    "resultexecution": "0",
    "enforcedexecution": "True",
    "runtimeexecution": "978",
    "descriptionexecution": "Execution log for podman-ktest"
  },
  "f67f55b5b8188c0e7aef6040cf9a72c36b8deebe": {
    "resultcheckpatch-parallel": "0",
    "enforcedcheckpatch-parallel": "False",
    "runtimecheckpatch-parallel": "96",
    "descriptioncheckpatch-parallel": "Run checkpatch.pl on the entire Lustre tree",
    "resultcontribution-report": "0",
    "enforcedcontribution-report": "False",
    "runtimecontribution-report": "17",
    "descriptioncontribution-report": "Fetch contribution statistics for Lustre tree",
    "resultlicense-status": "0",
    "enforcedlicense-status": "False",
    "runtimelicense-status": "22",
    "descriptionlicense-status": "Fetch license info for Lustre tree",
    "resultkernel-doc": "0",
    "enforcedkernel-doc": "False",
    "runtimekernel-doc": "19",
    "descriptionkernel-doc": "Check the number of kernel doc errors",
    "resultu24": "0",
    "enforcedu24": "True",
    "runtimeu24": "99",
    "descriptionu24": "Build Lustre (U24/OutOfTree)",
    "resultal2023": "0",
    "enforcedal2023": "True",
    "runtimeal2023": "89",
    "descriptional2023": "Build Lustre (AL2023/OutOfTree)",
    "resultlustre_mainline_strict": "1",
    "enforcedlustre_mainline_strict": "False",
    "runtimelustre_mainline_strict": "184",
    "descriptionlustre_mainline_strict": "Build Lustre (LLVM/OutOfTree/NoWarnings)",
    "resultlustre_mainline": "0",
    "enforcedlustre_mainline": "True",
    "runtimelustre_mainline": "188",
    "descriptionlustre_mainline": "Build Lustre (LLVM/OutOfTree)",
    "resultlustre_mainline_native": "0",
    "enforcedlustre_mainline_native": "True",
    "runtimelustre_mainline_native": "187",
    "descriptionlustre_mainline_native": "Build Lustre (InTree)",
    "resultclang-tidy": "0",
    "enforcedclang-tidy": "False",
    "runtimeclang-tidy": "87",
    "descriptionclang-tidy": "Run Clang Tidy",
    "resultcc-plugin": "127",
    "enforcedcc-plugin": "False",
    "runtimecc-plugin": "58",
    "descriptioncc-plugin": "Run Lustre LLVM Compiler Plugin",
    "resultboot": "0",
    "enforcedboot": "True",
    "runtimeboot": "67",
    "descriptionboot": "Job: boot",
    "resultllmount": "0",
    "enforcedllmount": "True",
    "runtimellmount": "151",
    "descriptionllmount": "Job: llmount",
    "resultmgs-setup": "0",
    "enforcedmgs-setup": "True",
    "runtimemgs-setup": "79",
    "descriptionmgs-setup": "Job: mgs-setup",
    "resultsanity-1": "0",
    "enforcedsanity-1": "True",
    "runtimesanity-1": "92",
    "descriptionsanity-1": "Job: sanity-1",
    "resultsanity-2": "0",
    "enforcedsanity-2": "True",
    "runtimesanity-2": "99",
    "descriptionsanity-2": "Job: sanity-2",
    "resultsanity-3": "0",
    "enforcedsanity-3": "True",
    "runtimesanity-3": "91",
    "descriptionsanity-3": "Job: sanity-3",
    "resultsanity-4": "0",
    "enforcedsanity-4": "True",
    "runtimesanity-4": "109",
    "descriptionsanity-4": "Job: sanity-4",
    "patch_revision": "f67f55b5b8188c0e7aef6040cf9a72c36b8deebe",
    "time_stamp": "1778533586",
    "total_runtime": "370",
    "change_id": "master-next",
    "subject": "Staging branch for new changes",
    "resultexecution": "0",
    "enforcedexecution": "True",
    "runtimeexecution": "370",
    "descriptionexecution": "Execution log for podman-ktest"
  }
}